MANIFEST.in
README.md
VERSION
requirements.txt
setup.cfg
setup.py
showit/__init__.py
showit/showit.py
showit.egg-info/PKG-INFO
showit.egg-info/SOURCES.txt
showit.egg-info/dependency_links.txt
showit.egg-info/requires.txt
showit.egg-info/top_level.txt
test/test_main.py