Metadata-Version: 1.0
Name: showit
Version: 1.1.3
Summary: simple and sensible display of images
Home-page: https://github.com/freeman-lab/showit
Author: freeman-lab
Author-email: the.freeman.lab@gmail.com
License: UNKNOWN
Platform: UNKNOWN
